{
  "project_info": {
    "project_number": "731006489646",
    "firebase_url": "https://android-d3fb9.firebaseio.com",
    "project_id": "android-d3fb9",
    "storage_bucket": "android-d3fb9.appspot.com"
  },
  "client": [
    {
      "client_info": {
        "mobilesdk_app_id": "1:731006489646:android:ca15bddadce9c412e6bbbf",
        "android_client_info": {
          "package_name": "com.example.loginsignup"
        }
      },
      "oauth_client": [
        {
          "client_id": "731006489646-mj8mevpmejjom543ugkigqo4vb3fbc3p.apps.googleusercontent.com",
          "client_type": 3
        }
      ],
      "api_key": [
        {
          "current_key": "AIzaSyD2eHBX29EJB9vXJH1nCcAauY6aTu_EzSo"
        }
      ],
      "services": {
        "appinvite_service": {
          "other_platform_oauth_client": [
            {
              "client_id": "731006489646-mj8mevpmejjom543ugkigqo4vb3fbc3p.apps.googleusercontent.com",
              "client_type": 3
            }
          ]
        }
      }
    }
  ],
  "configuration_version": "1"
}